{
"type": "FeatureCollection",
"name": "liguria_representative_point",
"crs": { "type": "name", "properties": { "name": "urn:ogc:def:crs:OGC:1.3:CRS84" } },
"features": [
{ "type": "Feature", "properties": { }, "geometry": { "type": "Point", "coordinates": [ 9.683912669396294, 44.227821698486515 ] } }
]
}
